graph_jsp_utils/__init__.py
graph_jsp_utils/disjunctive_graph_logger.py
graph_jsp_utils/jsp_custom_instance_details.py
graph_jsp_utils/jsp_custom_instance_generator.py
graph_jsp_utils/jsp_instance_details.py
graph_jsp_utils/jsp_instance_downloader.py
graph_jsp_utils/jsp_instance_parser.py
graph_jsp_utils/jsp_or_tools_solver.py
graph_jsp_utils/name_generator.py
graph_jsp_utils-0.0.1.dist-info/LICENSE
graph_jsp_utils-0.0.1.dist-info/METADATA
graph_jsp_utils-0.0.1.dist-info/WHEEL
graph_jsp_utils-0.0.1.dist-info/top_level.txt
graph_jsp_utils-0.0.1.dist-info/RECORD
